{
  "$schema": "./lab_data.schema.json",
  "title": "Leg Bones, Joints and Movements",
  "sections": [
    {
      "id": "week-6-1-hip-and-leg",
      "title": "WEEK 6.1 - HIP AND LEG",
      "data": [
        {
          "id": 0,
          "label": "WEEK 6.1 - HIP AND LEG",
          "children": [],
          "type": "none"
        },
        {
          "id": 1,
          "label": "6.1.1 - Intro Hip and Leg Bones",
          "load": "Pages/6_1_1_intro_leg_bones.html",
          "children": []
        },
        {
          "id": 2,
          "label": "6.1.2- Hip and Leg 2D Anatomy",
          "children": [
            {
              "id": 3,
              "label": "Coxal Bones (Os Coxae)",
              "type": "img",
              "sound": "Sounds/os_coxae.wav",
              "buttons": [
                {
                  "label": "Anterior and Posterior Complete",
                  "img": "Images/cox_bone.jpg"
                },
                {
                  "label": "Complete Skeleton 3D Animation",
                  "img": "gifs/os_coxae.gif"
                },
                {
                  "label": "Posterior with Sacrum",
                  "img": "Images/cox_bones_post.jpg"
                },
                {
                  "label": "3D Animation One Os Coxae",
                  "img": "gifs/coxal.gif"
                }
              ],
              "children": [
                {
                  "id": 4,
                  "label": "Acetabulum",
                  "type": "img",
                  "sound": "Sounds/acetabulum.wav",
                  "buttons": [
                    {
                      "label": "Anterior with Sacrum",
                      "img": "Images/acetab_comp_ant.jpg"
                    },
                    {
                      "label": "Lateral",
                      "img": "Images/acetabulum_lat.jpg"
                    },
                    {
                      "label": "Posterior",
                      "img": "Images/acetabulum_post.jpg"
                    }
                  ],
                  "children": []
                },
                {
                  "id": 5,
                  "label": "Anterior Inferior Iliac Spine",
                  "type": "img",
                  "sound": "Sounds/anterior_inferior_iliac_spine.wav",
                  "buttons": [
                    {
                      "label": "Anterior with Sacrum",
                      "img": "Images/ant_inf_iliac_spine_comp_ant.jpg"
                    },
                    {
                      "label": "Anterior",
                      "img": "Images/ant_inf_iliac_spine_ant.jpg"
                    },
                    {
                      "label": "Medial",
                      "img": "Images/ant_inf_iliac_spine_med.jpg"
                    },
                    {
                      "label": "Posterior",
                      "img": "Images/ant_inf_iliac_spine_post.jpg"
                    },
                    {
                      "label": "Lateral",
                      "img": "Images/ant_inf_iliac_spine_lat.jpg"
                    }
                  ],
                  "children": []
                },
                {
                  "id": 6,
                  "label": "Anterior Superior Iliac Spine",
                  "type": "img",
                  "sound": "Sounds/anterior_superior_iliac_spine.wav",
                  "buttons": [
                    {
                      "label": "Anterior with Sacrum",
                      "img": "Images/ant_sup_iliac_spine_comp_ant.jpg"
                    },
                    {
                      "label": "Anterior",
                      "img": "Images/ant_sup_iliac_spine_ant.jpg"
                    },
                    {
                      "label": "Medial",
                      "img": "Images/ant_sup_iliac_spine_med.jpg"
                    },
                    {
                      "label": "Posterior",
                      "img": "Images/ant_sup_iliac_spine_post.jpg"
                    },
                    {
                      "label": "Lateral",
                      "img": "Images/ant_sup_iliac_spine_lat.jpg"
                    }
                  ],
                  "children": []
                },
                {
                  "id": 7,
                  "label": "Auricular Surface",
                  "type": "img",
                  "sound": "Sounds/auricular_surface.wav",
                  "buttons": [
                    {
                      "label": "Anterior",
                      "img": "Images/auric_surface_ant.jpg"
                    },
                    {
                      "label": "Medial",
                      "img": "Images/auric_surface_med.jpg"
                    }
                  ],
                  "children": []
                },
                {
                  "id": 8,
                  "label": "Greater Sciatic Notch",
                  "type": "img",
                  "sound": "Sounds/greater_sciatic_notch.wav",
                  "buttons": [
                    {
                      "label": "Anterior with Sacrum",
                      "img": "Images/g_sciatic_notch_comp_ant.jpg"
                    },
                    {
                      "label": "Posterior with Sacrum",
                      "img": "Images/g_sciatic_notch_comp_post.jpg"
                    },
                    {
                      "label": "Anterior",
                      "img": "Images/great_sciatic_notch_ant.jpg"
                    },
                    {
                      "label": "Medial",
                      "img": "Images/great_sciatic_notch_med.jpg"
                    },
                    {
                      "label": "Posterior",
                      "img": "Images/great_sciatic_notch_post.jpg"
                    },
                    {
                      "label": "Lateral",
                      "img": "Images/great_sciatic_notch_lat.jpg"
                    }
                  ],
                  "children": []
                },
                {
                  "id": 9,
                  "label": "Iliac Crest",
                  "type": "img",
                  "sound": "Sounds/iliac_crest.wav",
                  "buttons": [
                    {
                      "label": "Anterior with Sacrum",
                      "img": "Images/iliac_crest_comp_ant.jpg"
                    },
                    {
                      "label": "Posterior with Sacrum",
                      "img": "Images/iliac_crest_comp_post.jpg"
                    },
                    {
                      "label": "Anterior",
                      "img": "Images/iliac_crest_ant.jpg"
                    },
                    {
                      "label": "Medial",
                      "img": "Images/iliac_crest_med.jpg"
                    },
                    {
                      "label": "Posterior",
                      "img": "Images/iliac_crest_post.jpg"
                    },
                    {
                      "label": "Lateral",
                      "img": "Images/iliac_crest_lat.jpg"
                    }
                  ],
                  "children": []
                },
                {
                  "id": 10,
                  "label": "Iliac Fossa",
                  "type": "img",
                  "sound": "Sounds/iliac_fossa.wav",
                  "buttons": [
                    {
                      "label": "Anterior with Sacrum",
                      "img": "Images/iliac_fossa_comp_ant.jpg"
                    },
                    {
                      "label": "Anterior",
                      "img": "Images/iliac_fossa_ant.jpg"
                    },
                    {
                      "label": "Medial",
                      "img": "Images/iliac_fossa_med.jpg"
                    }
                  ],
                  "children": []
                },
                {
                  "id": 11,
                  "label": "Ilium",
                  "type": "img",
                  "sound": "Sounds/ilium.wav",
                  "buttons": [
                    {
                      "label": "Anterior with Sacrum",
                      "img": "Images/ilium_comp_ant.jpg"
                    },
                    {
                      "label": "Posterior with Sacrum",
                      "img": "Images/ilium_comp_post.jpg"
                    },
                    {
                      "label": "Anterior",
                      "img": "Images/ilium_ant.jpg"
                    },
                    {
                      "label": "Medial",
                      "img": "Images/ilium_med.jpg"
                    },
                    {
                      "label": "Posterior",
                      "img": "Images/ilium_post.jpg"
                    },
                    {
                      "label": "Lateral",
                      "img": "Images/ilium_lat.jpg"
                    }
                  ],
                  "children": []
                },
                {
                  "id": 12,
                  "label": "Inferior Pubic Ramus",
                  "type": "img",
                  "sound": "Sounds/inferior_pubic_ramus.wav",
                  "buttons": [
                    {
                      "label": "Anterior with Sacrum",
                      "img": "Images/inf_pubic_ramus_comp_ant.jpg"
                    },
                    {
                      "label": "Posterior with Sacrum",
                      "img": "Images/inf_pubic_ramus_comp_post.jpg"
                    },
                    {
                      "label": "Anterior",
                      "img": "Images/inf_pubic_ramus_ant.jpg"
                    },
                    {
                      "label": "Medial",
                      "img": "Images/inf_pubic_ramus_med.jpg"
                    },
                    {
                      "label": "Lateral",
                      "img": "Images/inf_pubic_ramus_lat.jpg"
                    }
                  ],
                  "children": []
                },
                {
                  "id": 13,
                  "label": "Ischial Ramus",
                  "type": "img",
                  "sound": "Sounds/ischial_ramus.wav",
                  "buttons": [
                    {
                      "label": "Anterior with Sacrum",
                      "img": "Images/ischial_ramus_comp_ant.jpg"
                    },
                    {
                      "label": "Posterior with Sacrum",
                      "img": "Images/isch_ramus_comp_post.jpg"
                    },
                    {
                      "label": "Anterior",
                      "img": "Images/ischial_ramus_ant.jpg"
                    },
                    {
                      "label": "Medial",
                      "img": "Images/ischial_ramus_med.jpg"
                    },
                    {
                      "label": "Lateral",
                      "img": "Images/ischial_ramus_lat.jpg"
                    }
                  ],
                  "children": []
                },
                {
                  "id": 14,
                  "label": "Ischial Spine",
                  "type": "img",
                  "sound": "Sounds/ischial_spine.wav",
                  "buttons": [
                    {
                      "label": "Anterior",
                      "img": "Images/ischial_spine_ant.jpg"
                    },
                    {
                      "label": "Medial",
                      "img": "Images/ischial_spine_med.jpg"
                    },
                    {
                      "label": "Posterior",
                      "img": "Images/ischial_spine_post.jpg"
                    },
                    {
                      "label": "Posterior with Sacrum",
                      "img": "Images/isch_spine_comp_post.jpg"
                    }
                  ],
                  "children": []
                },
                {
                  "id": 15,
                  "label": "Ischial Tuberosity",
                  "type": "img",
                  "sound": "Sounds/ischial_tuberosity.wav",
                  "buttons": [
                    {
                      "label": "Anterior with Sacrum",
                      "img": "Images/ischial_tuberos_comp_ant.jpg"
                    },
                    {
                      "label": "Posterior with Sacrum",
                      "img": "Images/isch_tuber_comp_post.jpg"
                    },
                    {
                      "label": "Anterior",
                      "img": "Images/ischial_tuberos_ant.jpg"
                    },
                    {
                      "label": "Medial",
                      "img": "Images/ischial_tuberos_med.jpg"
                    },
                    {
                      "label": "Posterior",
                      "img": "Images/ischial_tuberos_post.jpg"
                    },
                    {
                      "label": "Lateral",
                      "img": "Images/ischial_tuberos_lat.jpg"
                    }
                  ],
                  "children": []
                },
                {
                  "id": 16,
                  "label": "Ischium",
                  "type": "img",
                  "sound": "Sounds/ischium.wav",
                  "buttons": [
                    {
                      "label": "Anterior with Sacrum",
                      "img": "Images/ischium_comp_ant.jpg"
                    },
                    {
                      "label": "Posterior with Sacrum",
                      "img": "Images/ischium_comp_post.jpg"
                    },
                    {
                      "label": "Anterior",
                      "img": "Images/ischium_ant.jpg"
                    },
                    {
                      "label": "Medial",
                      "img": "Images/ischium_med.jpg"
                    },
                    {
                      "label": "Posterior",
                      "img": "Images/ischium_post.jpg"
                    },
                    {
                      "label": "Lateral",
                      "img": "Images/ischium_lat.jpg"
                    }
                  ],
                  "children": []
                },
                {
                  "id": 17,
                  "label": "Lesser Sciatic Notch",
                  "type": "img",
                  "sound": "Sounds/lesser_sciatic_notch.wav",
                  "buttons": [
                    {
                      "label": "Anterior",
                      "img": "Images/less_sciatic_notch_ant.jpg"
                    },
                    {
                      "label": "Medial",
                      "img": "Images/less_sciatic_notch_med.jpg"
                    },
                    {
                      "label": "Posterior",
                      "img": "Images/less_sciatic_notch_post.jpg"
                    },
                    {
                      "label": "Posterior with Sacrum",
                      "img": "Images/l_sciatic_notch_comp_post.jpg"
                    }
                  ],
                  "children": []
                },
                {
                  "id": 18,
                  "label": "Obturator Foramen",
                  "type": "img",
                  "sound": "Sounds/obturator_foramen.wav",
                  "buttons": [
                    {
                      "label": "Anterior with Sacrum",
                      "img": "Images/obt_foramen_comp_ant.jpg"
                    },
                    {
                      "label": "Posterior with Sacrum",
                      "img": "Images/obt_foramen_comp_post.jpg"
                    },
                    {
                      "label": "Anterior",
                      "img": "Images/obt_foramen_ant.jpg"
                    },
                    {
                      "label": "Medial",
                      "img": "Images/obt_foramen_med.jpg"
                    },
                    {
                      "label": "Lateral",
                      "img": "Images/obt_foramen_lat.jpg"
                    }
                  ],
                  "children": []
                },
                {
                  "id": 19,
                  "label": "Posterior Inferior Iliac Spine",
                  "type": "img",
                  "sound": "Sounds/posterior_inferior_iliac_spine.wav",
                  "buttons": [
                    {
                      "label": "Anterior",
                      "img": "Images/post_inf_iliac_spine_ant.jpg"
                    },
                    {
                      "label": "Medial",
                      "img": "Images/post_inf_iliac_spine_med.jpg"
                    },
                    {
                      "label": "Posterior",
                      "img": "Images/post_inf_iliac_spine_post.jpg"
                    },
                    {
                      "label": "Lateral",
                      "img": "Images/post_inf_iliac_spine_lat.jpg"
                    },
                    {
                      "label": "Posterior with Sacrum",
                      "img": "Images/post_inf_iliac_spine_comp_post.jpg"
                    }
                  ],
                  "children": []
                },
                {
                  "id": 20,
                  "label": "Posterior Superior Iliac Spine",
                  "type": "img",
                  "sound": "Sounds/posterior_superior_iliac_spine.wav",
                  "buttons": [
                    {
                      "label": "Anterior",
                      "img": "Images/post_sup_iliac_spine_ant.jpg"
                    },
                    {
                      "label": "Medial",
                      "img": "Images/post_sup_iliac_spine_med.jpg"
                    },
                    {
                      "label": "Posterior",
                      "img": "Images/post_sup_iliac_spine_post.jpg"
                    },
                    {
                      "label": "Lateral",
                      "img": "Images/post_sup_iliac_spine_lat.jpg"
                    },
                    {
                      "label": "Posterior with Sacrum",
                      "img": "Images/post_sup_iliac_spine_comp_post.jpg"
                    }
                  ],
                  "children": []
                },
                {
                  "id": 21,
                  "label": "Pubic Crest",
                  "type": "img",
                  "sound": "Sounds/pubic_crest.wav",
                  "buttons": [
                    {
                      "label": "Anterior with Sacrum",
                      "img": "Images/pubic_crest_comp_ant.jpg"
                    },
                    {
                      "label": "Anterior",
                      "img": "Images/pubic_crest_ant.jpg"
                    },
                    {
                      "label": "Medial",
                      "img": "Images/pubic_crest_med.jpg"
                    },
                    {
                      "label": "Lateral",
                      "img": "Images/pubic_crest_lat.jpg"
                    }
                  ],
                  "children": []
                },
                {
                  "id": 22,
                  "label": "Pubis",
                  "type": "img",
                  "sound": "Sounds/pubis.wav",
                  "buttons": [
                    {
                      "label": "Anterior with Sacrum",
                      "img": "Images/pubis_comp_ant.jpg"
                    },
                    {
                      "label": "Anterior",
                      "img": "Images/pubis_ant.jpg"
                    },
                    {
                      "label": "Medial",
                      "img": "Images/pubis_med.jpg"
                    },
                    {
                      "label": "Posterior",
                      "img": "Images/pubis_post.jpg"
                    },
                    {
                      "label": "Lateral",
                      "img": "Images/pubis_lat.jpg"
                    }
                  ],
                  "children": []
                },
                {
                  "id": 23,
                  "label": "Superior Pubic Ramus",
                  "type": "img",
                  "sound": "Sounds/superior_pubic_ramus.wav",
                  "buttons": [
                    {
                      "label": "Anterior with Sacrum",
                      "img": "Images/sup_pubic_ramus_comp_ant.jpg"
                    },
                    {
                      "label": "Anterior",
                      "img": "Images/sup_pubic_ramus_ant.jpg"
                    },
                    {
                      "label": "Medial",
                      "img": "Images/sup_pubic_ramus_med.jpg"
                    },
                    {
                      "label": "Lateral",
                      "img": "Images/sup_pubic_ramus_lat.jpg"
                    }
                  ],
                  "children": []
                },
                {
                  "id": 24,
                  "label": "Symphysis Pubis",
                  "type": "img",
                  "sound": "Sounds/symphysis_pubis.wav",
                  "buttons": [
                    {
                      "label": "Anterior with Sacrum",
                      "img": "Images/symphysis_pubis_comp_ant.jpg"
                    },
                    {
                      "label": "Anterior",
                      "img": "Images/symphysis_pubis_ant.jpg"
                    },
                    {
                      "label": "Medial",
                      "img": "Images/symphysis_pubis_med.jpg"
                    }
                  ],
                  "children": []
                }
              ]
            },
            {
              "id": 25,
              "label": "Femur",
              "type": "img",
              "sound": "Sounds/femur.wav",
              "buttons": [
                {
                  "label": "Anterior and Posterior-Complete",
                  "img": "Images/femur.jpg"
                },
                {
                  "label": "Anterior and Posterior-Zoom",
                  "img": "Images/femur-zoom.jpg"
                },
                {
                  "label": "3D Animation",
                  "img": "gifs/femur.gif"
                }
              ],
              "children": [
                {
                  "id": 26,
                  "label": "Body",
                  "type": "img",
                  "sound": "Sounds/body.wav",
                  "buttons": [
                    {
                      "label": "",
                      "img": "Images/body_femur.jpg"
                    }
                  ],
                  "children": []
                },
                {
                  "id": 27,
                  "label": "Fovea Capitis",
                  "type": "img",
                  "sound": "Sounds/fovea_capitis.wav",
                  "buttons": [
                    {
                      "label": "",
                      "img": "Images/fovea_capitis2.jpg"
                    }
                  ],
                  "children": []
                },
                {
                  "id": 28,
                  "label": "Gluteal Tuberosity",
                  "type": "img",
                  "sound": "Sounds/gluteal_tuberosity.wav",
                  "buttons": [
                    {
                      "label": "",
                      "img": "Images/glut_tuberosity.jpg"
                    }
                  ],
                  "children": []
                },
                {
                  "id": 29,
                  "label": "Greater Trochanter",
                  "type": "img",
                  "sound": "Sounds/greater_trochanter.wav",
                  "buttons": [
                    {
                      "label": "",
                      "img": "Images/g_trochanter.jpg"
                    }
                  ],
                  "children": []
                },
                {
                  "id": 30,
                  "label": "Head",
                  "type": "img",
                  "sound": "Sounds/head.wav",
                  "buttons": [
                    {
                      "label": "",
                      "img": "Images/head_femur.jpg"
                    }
                  ],
                  "children": []
                },
                {
                  "id": 31,
                  "label": "Intercondylar Fossa",
                  "type": "img",
                  "sound": "Sounds/intercondylar_fossa.wav",
                  "buttons": [
                    {
                      "label": "",
                      "img": "Images/intercon_fossa.jpg"
                    }
                  ],
                  "children": []
                },
                {
                  "id": 32,
                  "label": "Intertrochanteric Crest",
                  "type": "img",
                  "sound": "Sounds/intertrochanteric_crest.wav",
                  "buttons": [
                    {
                      "label": "",
                      "img": "Images/intertroch_crest.jpg"
                    }
                  ],
                  "children": []
                },
                {
                  "id": 33,
                  "label": "Lateral Condyle",
                  "type": "img",
                  "sound": "Sounds/lateral_condyle.wav",
                  "buttons": [
                    {
                      "label": "",
                      "img": "Images/lat_condyle_femur.jpg"
                    }
                  ],
                  "children": []
                },
                {
                  "id": 34,
                  "label": "Lateral Epicondyle",
                  "type": "img",
                  "sound": "Sounds/",
                  "buttons": [
                    {
                      "label": "",
                      "img": "Images/lat_epicondyle_femur.jpg"
                    }
                  ],
                  "children": []
                },
                {
                  "id": 35,
                  "label": "Lesser Trochanter",
                  "type": "img",
                  "sound": "Sounds/lesser_trochanter.wav",
                  "buttons": [
                    {
                      "label": "",
                      "img": "Images/l_trochanter.jpg"
                    }
                  ],
                  "children": []
                },
                {
                  "id": 36,
                  "label": "Linea Aspera",
                  "type": "img",
                  "sound": "Sounds/linea_aspera.wav",
                  "buttons": [
                    {
                      "label": "",
                      "img": "Images/linea_aspera.jpg"
                    }
                  ],
                  "children": []
                },
                {
                  "id": 37,
                  "label": "Medial Condyle",
                  "type": "img",
                  "sound": "Sounds/medial_condyle.wav",
                  "buttons": [
                    {
                      "label": "",
                      "img": "Images/med_condyle_femur.jpg"
                    }
                  ],
                  "children": []
                },
                {
                  "id": 38,
                  "label": "Medial Epicondyle",
                  "type": "img",
                  "sound": "Sounds/medial_epicondyle.wav",
                  "buttons": [
                    {
                      "label": "",
                      "img": "Images/med_epicondyle_femur.jpg"
                    }
                  ],
                  "children": []
                },
                {
                  "id": 39,
                  "label": "Neck",
                  "type": "img",
                  "sound": "Sounds/neck.wav",
                  "buttons": [
                    {
                      "label": "",
                      "img": "Images/neck_femur.jpg"
                    }
                  ],
                  "children": []
                },
                {
                  "id": 40,
                  "label": "Patellar Groove",
                  "type": "img",
                  "sound": "Sounds/patellar_groove.wav",
                  "buttons": [
                    {
                      "label": "",
                      "img": "Images/patellar_groove.jpg"
                    }
                  ],
                  "children": []
                }
              ]
            },
            {
              "id": 41,
              "label": "Patella",
              "type": "img",
              "sound": "Sounds/patella.wav",
              "buttons": [
                {
                  "label": "Complete Skeleton",
                  "img": "Images/patella.jpg"
                },
                {
                  "label": "Anterior",
                  "img": "Images/patella_ant.jpg"
                },
                {
                  "label": "Posterior",
                  "img": "Images/patella_post.jpg"
                },
                {
                  "label": "3D Animation",
                  "img": "Images/Patella.gif"
                }
              ],
              "children": [
                {
                  "id": 42,
                  "label": "Anterior Surface",
                  "type": "img",
                  "sound": "Sounds/anterior_surface.wav",
                  "buttons": [
                    {
                      "label": "",
                      "img": "Images/ant_surface.jpg"
                    }
                  ],
                  "children": []
                },
                {
                  "id": 43,
                  "label": "Apex",
                  "type": "img",
                  "sound": "Sounds/apex.wav",
                  "buttons": [
                    {
                      "label": "Anterior",
                      "img": "Images/apex_ant_pat.jpg"
                    },
                    {
                      "label": "Posterior",
                      "img": "Images/apex_post_pat.jpg"
                    }
                  ],
                  "children": []
                },
                {
                  "id": 44,
                  "label": "Base",
                  "type": "img",
                  "sound": "Sounds/base.wav",
                  "buttons": [
                    {
                      "label": "Anterior",
                      "img": "Images/base_ant_pat.jpg"
                    },
                    {
                      "label": "Posterior",
                      "img": "Images/base_ant_pat.jpg"
                    }
                  ],
                  "children": []
                },
                {
                  "id": 45,
                  "label": "Posterior Surface",
                  "type": "img",
                  "sound": "Sounds/posterior_surface.wav",
                  "buttons": [
                    {
                      "label": "",
                      "img": "Images/post_surface.jpg"
                    }
                  ],
                  "children": []
                },
                {
                  "id": 46,
                  "label": "Lateral Articular Facet",
                  "type": "img",
                  "sound": "Sounds/lateral_articular_facet.wav",
                  "buttons": [
                    {
                      "label": "",
                      "img": "Images/lat_artic_facet_post_pat.jpg"
                    }
                  ],
                  "children": []
                },
                {
                  "id": 47,
                  "label": "Medial Articular Facet",
                  "type": "img",
                  "sound": "Sounds/medial_articular_facet.wav",
                  "buttons": [
                    {
                      "label": "",
                      "img": "Images/med_artic_facet_post_pat.jpg"
                    }
                  ],
                  "children": []
                }
              ]
            },
            {
              "id": 48,
              "label": "Tibia",
              "type": "img",
              "sound": "Sounds/tibia.wav",
              "buttons": [
                {
                  "label": "Complete Skeleton",
                  "img": "Images/tibia.jpg"
                },
                {
                  "label": "Overview",
                  "img": "Images/tibia-zoom.jpg"
                },
                {
                  "label": "Anterior with Leg",
                  "img": "Images/tibia_comp_ant.jpg"
                },
                {
                  "label": "Medial with Leg",
                  "img": "Images/tibia_comp_med.jpg"
                },
                {
                  "label": "Lateral with Leg",
                  "img": "Images/tibia_comp_lat.jpg"
                },
                {
                  "label": "3D Animation",
                  "img": "gifs/tibia.gif"
                }
              ],
              "children": [
                {
                  "id": 49,
                  "label": "Anterior Crest",
                  "type": "img",
                  "sound": "Sounds/anterior_crest.wav",
                  "buttons": [
                    {
                      "label": "Overview",
                      "img": "Images/ant_crest.jpg"
                    },
                    {
                      "label": "Anterior with Leg",
                      "img": "Images/ant_crest_comp_ant.jpg"
                    },
                    {
                      "label": "Medial with Leg",
                      "img": "Images/ant_crest_comp_med.jpg"
                    },
                    {
                      "label": "Lateral with Leg",
                      "img": "Images/ant_crest_comp_lat.jpg"
                    }
                  ],
                  "children": []
                },
                {
                  "id": 50,
                  "label": "Fibular Notch",
                  "type": "img",
                  "sound": "Sounds/fibular_notch.wav",
                  "buttons": [
                    {
                      "label": "Overview",
                      "img": "Images/fib_notch.jpg"
                    },
                    {
                      "label": "Lateral with Leg",
                      "img": "Images/fib_notch_leg.jpg"
                    }
                  ],
                  "children": []
                },
                {
                  "id": 51,
                  "label": "Intercondylar Eminence",
                  "type": "img",
                  "sound": "Sounds/intercondylar_eminence.wav",
                  "buttons": [
                    {
                      "label": "Overview",
                      "img": "Images/inter_eminence.jpg"
                    },
                    {
                      "label": "Anterior with Leg",
                      "img": "Images/intercond_eminence_comp_ant.jpg"
                    },
                    {
                      "label": "Medial with Leg",
                      "img": "Images/intercond_eminence_comp_med.jpg"
                    },
                    {
                      "label": "Lateral with Leg",
                      "img": "Images/intercond_eminence_comp_lat.jpg"
                    }
                  ],
                  "children": []
                },
                {
                  "id": 52,
                  "label": "Lateral Condyle",
                  "type": "img",
                  "sound": "Sounds/lateral_condyle.wav",
                  "buttons": [
                    {
                      "label": "Overview",
                      "img": "Images/lat_condyle_tibia.jpg"
                    },
                    {
                      "label": "Anterior with Leg",
                      "img": "Images/lat_condyle_comp_ant.jpg"
                    },
                    {
                      "label": "Lateral with Leg",
                      "img": "Images/lat_condyle_comp_lat.jpg"
                    }
                  ],
                  "children": []
                },
                {
                  "id": 53,
                  "label": "Medial Condyle",
                  "type": "img",
                  "sound": "Sounds/medial_condyle.wav",
                  "buttons": [
                    {
                      "label": "Overview",
                      "img": "Images/med_condyle_tibia.jpg"
                    },
                    {
                      "label": "Anterior with Leg",
                      "img": "Images/med_condyle_comp_ant.jpg"
                    },
                    {
                      "label": "Medial with Leg",
                      "img": "Images/med_condyle_comp_med.jpg"
                    }
                  ],
                  "children": []
                },
                {
                  "id": 54,
                  "label": "Medial Malleolus",
                  "type": "img",
                  "sound": "Sounds/medial_malleolus.wav",
                  "buttons": [
                    {
                      "label": "Overview",
                      "img": "Images/med_malleolus.jpg"
                    },
                    {
                      "label": "Anterior with Leg",
                      "img": "Images/med_malleolus_comp_ant.jpg"
                    },
                    {
                      "label": "Medial with Leg",
                      "img": "Images/med_malleolus_comp_med.jpg"
                    }
                  ],
                  "children": []
                },
                {
                  "id": 55,
                  "label": "Tibial Tuberosity",
                  "type": "img",
                  "sound": "Sounds/tibial_tuberosity.wav",
                  "buttons": [
                    {
                      "label": "Overview",
                      "img": "Images/tib_tuberosity.jpg"
                    },
                    {
                      "label": "Anterior with Leg",
                      "img": "Images/tib_tuber_comp_ant.jpg"
                    },
                    {
                      "label": "Medial with Leg",
                      "img": "Images/tib_tuber_comp_med.jpg"
                    },
                    {
                      "label": "Lateral with Leg",
                      "img": "Images/tib_tuber_comp_lat.jpg"
                    }
                  ],
                  "children": []
                }
              ]
            },
            {
              "id": 56,
              "label": "Fibula",
              "type": "img",
              "sound": "Sounds/fibula.wav",
              "buttons": [
                {
                  "label": "Complete Skeleton",
                  "img": "Images/fibula.jpg"
                },
                {
                  "label": "Anterior and Posterior",
                  "img": "Images/fibula-zoom.jpg"
                },
                {
                  "label": "Anterior with Leg",
                  "img": "Images/fibula_comp_ant.jpg"
                },
                {
                  "label": "Medial with Leg",
                  "img": "Images/fibula_comp_med.jpg"
                },
                {
                  "label": "Lateral with Leg",
                  "img": "Images/fibula_comp_lat.jpg"
                },
                {
                  "label": "3D Animation",
                  "img": "gifs/fibula.gif"
                }
              ],
              "children": [
                {
                  "id": 57,
                  "label": "Head",
                  "type": "img",
                  "sound": "Sounds/head.wav",
                  "buttons": [
                    {
                      "label": "Anterior and Posterior",
                      "img": "Images/head_fibula.jpg"
                    },
                    {
                      "label": "Anterior with Leg",
                      "img": "Images/fib_head_comp_ant.jpg"
                    },
                    {
                      "label": "Lateral with Leg",
                      "img": "Images/fib_head_comp_lat.jpg"
                    }
                  ],
                  "children": []
                },
                {
                  "id": 58,
                  "label": "Lateral Malleolus",
                  "type": "img",
                  "sound": "Sounds/lateral_malleolus.wav",
                  "buttons": [
                    {
                      "label": "Anterior and Posterior",
                      "img": "Images/lat_malleolus.jpg"
                    },
                    {
                      "label": "Anterior with Leg",
                      "img": "Images/lat_malleolus_comp_ant.jpg"
                    },
                    {
                      "label": "Lateral with Leg",
                      "img": "Images/lat_malleolus_comp_lat.jpg"
                    }
                  ],
                  "children": []
                }
              ]
            },
            {
              "id": 59,
              "label": "Tarsal Bones",
              "sound": "Sounds/tarsals.wav",
              "children": [
                {
                  "id": 60,
                  "label": "Talus",
                  "type": "img",
                  "sound": "Sounds/talus.wav",
                  "buttons": [
                    {
                      "label": "",
                      "img": "Images/talus.jpg"
                    }
                  ],
                  "children": []
                },
                {
                  "id": 61,
                  "label": "Calcaneus",
                  "type": "img",
                  "sound": "Sounds/calcaneous.wav",
                  "buttons": [
                    {
                      "label": "",
                      "img": "Images/calcaneous.jpg"
                    }
                  ],
                  "children": []
                },
                {
                  "id": 62,
                  "label": "Navicular",
                  "type": "img",
                  "sound": "Sounds/navicular.wav",
                  "buttons": [
                    {
                      "label": "",
                      "img": "Images/navicular.jpg"
                    }
                  ],
                  "children": []
                },
                {
                  "id": 63,
                  "label": "Medial Cuneiform",
                  "type": "img",
                  "sound": "Sounds/medial_cune.wav",
                  "buttons": [
                    {
                      "label": "",
                      "img": "Images/med_cuneiform.jpg"
                    }
                  ],
                  "children": []
                },
                {
                  "id": 64,
                  "label": "Intermediate Cuneiform",
                  "type": "img",
                  "sound": "Sounds/intermediate_cune.wav",
                  "buttons": [
                    {
                      "label": "",
                      "img": "Images/inter_cuneiform.jpg"
                    }
                  ],
                  "children": []
                },
                {
                  "id": 65,
                  "label": "Lateral Cuneiform",
                  "type": "img",
                  "sound": "Sounds/lateral_cune.wav",
                  "buttons": [
                    {
                      "label": "",
                      "img": "Images/lat_cuneiform.jpg"
                    }
                  ],
                  "children": []
                },
                {
                  "id": 66,
                  "label": "Cuboid",
                  "type": "img",
                  "sound": "Sounds/cuboid.wav",
                  "buttons": [
                    {
                      "label": "",
                      "img": "Images/cuboid.jpg"
                    }
                  ],
                  "children": []
                }
              ],
              "type": "none"
            },
            {
              "id": 67,
              "label": "Metatarsals",
              "type": "img",
              "sound": "Sounds/metatarsals.wav",
              "buttons": [
                {
                  "label": "Complete Skeleton",
                  "img": "Images/metatarsals.jpg"
                },
                {
                  "label": "Superior and Inferior",
                  "img": "Images/metatarsals-zoom.jpg"
                },
                {
                  "label": "Anterior with Leg",
                  "img": "Images/metatarsals_comp_ant.jpg"
                },
                {
                  "label": "Medial with Leg",
                  "img": "Images/metatarsals_comp_med.jpg"
                },
                {
                  "label": "Lateral with Leg",
                  "img": "Images/metatarsals_comp_lat.jpg"
                }
              ],
              "children": [
                {
                  "id": 68,
                  "label": "Metatarsal 1",
                  "type": "img",
                  "sound": "Sounds/metatarsals.wav",
                  "buttons": [
                    {
                      "label": "",
                      "img": "Images/first_metatarsal.jpg"
                    }
                  ],
                  "children": []
                },
                {
                  "id": 69,
                  "label": "Sesamoid Bones",
                  "type": "img",
                  "buttons": [
                    {
                      "label": "Illustration 1",
                      "img": "Images/Sesamoidbones_Sobo_.jpg"
                    },
                    {
                      "label": "Photo with leg bones",
                      "img": "Images/foot_letg_sesamoids.jpg"
                    },
                    {
                      "label": "Xray Photo",
                      "img": "Images/SesamoidBonesOfFoot.jpg"
                    }
                  ],
                  "children": []
                },
                {
                  "id": 70,
                  "label": "Metatarsal 2",
                  "type": "img",
                  "sound": "Sounds/metatarsals.wav",
                  "buttons": [
                    {
                      "label": "",
                      "img": "Images/second_metatarsal.jpg"
                    }
                  ],
                  "children": []
                },
                {
                  "id": 71,
                  "label": "Metatarsal 3",
                  "type": "img",
                  "sound": "Sounds/metatarsals.wav",
                  "buttons": [
                    {
                      "label": "",
                      "img": "Images/third_metatarsal.jpg"
                    }
                  ],
                  "children": []
                },
                {
                  "id": 72,
                  "label": "Metatarsal 4",
                  "type": "img",
                  "sound": "Sounds/metatarsals.wav",
                  "buttons": [
                    {
                      "label": "",
                      "img": "Images/fourth_metatarsal.jpg"
                    }
                  ],
                  "children": []
                },
                {
                  "id": 73,
                  "label": "Metatarsal 5",
                  "type": "img",
                  "sound": "Sounds/metatarsals.wav",
                  "buttons": [
                    {
                      "label": "",
                      "img": "Images/fifth_metatarsal.jpg"
                    }
                  ],
                  "children": []
                }
              ]
            },
            {
              "id": 74,
              "label": "Digits (Phalanges)",
              "type": "img",
              "sound": "Sounds/digits.wav",
              "buttons": [
                {
                  "label": "Complete Skeleton",
                  "img": "Images/digits.jpg"
                },
                {
                  "label": "Superior and Inferior",
                  "img": "Images/digits-zoom.jpg"
                },
                {
                  "label": "Anterior",
                  "img": "Images/digits_comp_ant.jpg"
                },
                {
                  "label": "Medial",
                  "img": "Images/digits_comp_med.jpg"
                },
                {
                  "label": "Lateral",
                  "img": "Images/digits_comp_lat.jpg"
                }
              ],
              "children": [
                {
                  "id": 75,
                  "label": "Distal Phalanx",
                  "type": "img",
                  "sound": "Sounds/distal_phalanx.wav",
                  "buttons": [
                    {
                      "label": "",
                      "img": "Images/dist_phalan.jpg"
                    }
                  ],
                  "children": []
                },
                {
                  "id": 76,
                  "label": "Middle Phalanx",
                  "type": "img",
                  "sound": "Sounds/middle_phalanx.wav",
                  "buttons": [
                    {
                      "label": "",
                      "img": "Images/mid_phalan.jpg"
                    }
                  ],
                  "children": []
                },
                {
                  "id": 77,
                  "label": "Proximal Phalanx",
                  "type": "img",
                  "sound": "Sounds/proximal_phalanx.wav",
                  "buttons": [
                    {
                      "label": "",
                      "img": "Images/prox_phalan.jpg"
                    }
                  ],
                  "children": []
                }
              ]
            }
          ],
          "type": "none"
        },
        {
          "id": 78,
          "label": "6.1.3 - Hip and Leg 3D Anatomy",
          "type": "none",
          "child_items": [
            {
              "page": "https://content.byui.edu/file/ad4a036b-1100-473e-b25e-7a7b8b8f9936/1/Leg%20Bones/index.html"
            }
          ],
          "children": []
        },
        {
          "id": 79,
          "label": "6.1.4 - Intro Joints and Movements",
          "load": "Pages/6_1_4_intro_joints_mvts.html",
          "children": []
        },
        {
          "id": 80,
          "label": "6.1.5 - Joints",
          "children": [
            {
              "id": 81,
              "label": "Cartilaginous Joints",
              "load": "Pages/Cartilaginous.html",
              "children": [
                {
                  "id": 82,
                  "label": "Symphysis Joints",
                  "load": "Pages/Symphysis.html",
                  "children": []
                },
                {
                  "id": 83,
                  "label": "Synchondrosis Joints",
                  "load": "Pages/synchondrosis.html",
                  "children": []
                }
              ]
            },
            {
              "id": 84,
              "label": "Fibrous Joints",
              "load": "Pages/Fibrous.html",
              "children": [
                {
                  "id": 85,
                  "label": "Gomphoses",
                  "load": "Pages/Gomphosis.html",
                  "children": []
                },
                {
                  "id": 86,
                  "label": "Sutures",
                  "load": "Pages/Suture.html",
                  "children": []
                },
                {
                  "id": 87,
                  "label": "Syndesmosis",
                  "load": "Pages/syndesmoses.html",
                  "children": []
                }
              ]
            },
            {
              "id": 88,
              "label": "Synovial Joints",
              "load": "Pages/synovial.html",
              "children": [
                {
                  "id": 89,
                  "label": "Ball and Socket Joint",
                  "load": "Pages/ball_socket.html",
                  "children": []
                },
                {
                  "id": 90,
                  "label": "Ellipsoid (Condyloid) Joints",
                  "load": "Pages/ellipsoid.html",
                  "children": []
                },
                {
                  "id": 91,
                  "label": "Hinge Joint",
                  "load": "Pages/hinge.html",
                  "children": []
                },
                {
                  "id": 92,
                  "label": "Pivot Joint",
                  "load": "Pages/pivot.html",
                  "children": []
                },
                {
                  "id": 93,
                  "label": "Plane (Gliding) Joint",
                  "load": "Pages/plane.html",
                  "children": []
                },
                {
                  "id": 94,
                  "label": "Saddle Joint",
                  "load": "Pages/saddle.html",
                  "children": []
                }
              ]
            }
          ],
          "type": "none"
        },
        {
          "id": 95,
          "label": "6.1.6 - Movements",
          "children": [
            {
              "id": 96,
              "label": "Abduction and Adduction",
              "children": [
                {
                  "id": 97,
                  "label": "Abduction",
                  "type": "img",
                  "buttons": [
                    {
                      "label": "Shoulder Abduction",
                      "img": "Images/abduction.gif"
                    },
                    {
                      "label": "Hand Abduction",
                      "img": "Images/hand_abduction.gif"
                    }
                  ],
                  "children": []
                },
                {
                  "id": 98,
                  "label": "Adduction",
                  "type": "img",
                  "buttons": [
                    {
                      "label": "Shoulder Adduction",
                      "img": "Images/adduction.gif"
                    },
                    {
                      "label": "Hand Adduction",
                      "img": "Images/hand_adduction.gif"
                    }
                  ],
                  "children": []
                }
              ],
              "type": "none"
            },
            {
              "id": 99,
              "label": "Circumduction",
              "type": "img",
              "buttons": [
                {
                  "label": "",
                  "img": "Images/circumduction.gif"
                }
              ],
              "children": []
            },
            {
              "id": 100,
              "label": "Dorsiflexion and Plantarflexion",
              "children": [
                {
                  "id": 101,
                  "label": "Dorsiflexion",
                  "type": "img",
                  "buttons": [
                    {
                      "label": "",
                      "img": "Images/dorsiflexion.gif"
                    }
                  ],
                  "children": []
                },
                {
                  "id": 102,
                  "label": "Plantarflexion",
                  "type": "img",
                  "buttons": [
                    {
                      "label": "",
                      "img": "Images/plantarflexion.gif"
                    }
                  ],
                  "children": []
                }
              ],
              "type": "none"
            },
            {
              "id": 103,
              "label": "Elevation and Depression",
              "children": [
                {
                  "id": 104,
                  "label": "Elevation",
                  "type": "img",
                  "buttons": [
                    {
                      "label": "",
                      "img": "Images/elevation.gif"
                    }
                  ],
                  "children": []
                },
                {
                  "id": 105,
                  "label": "Depression",
                  "type": "img",
                  "buttons": [
                    {
                      "label": "",
                      "img": "Images/depression.gif"
                    }
                  ],
                  "children": []
                }
              ],
              "type": "none"
            },
            {
              "id": 106,
              "label": "Flexion and Extension",
              "children": [
                {
                  "id": 107,
                  "label": "Flexion",
                  "type": "img",
                  "buttons": [
                    {
                      "label": "",
                      "img": "Images/flexion.gif"
                    }
                  ],
                  "children": []
                },
                {
                  "id": 108,
                  "label": "Extenstion",
                  "type": "img",
                  "buttons": [
                    {
                      "label": "",
                      "img": "Images/extension.gif"
                    }
                  ],
                  "children": []
                }
              ],
              "type": "none"
            },
            {
              "id": 109,
              "label": "Inversion and Eversion",
              "children": [
                {
                  "id": 110,
                  "label": "Inversion",
                  "type": "img",
                  "buttons": [
                    {
                      "label": "",
                      "img": "Images/inversion.gif"
                    }
                  ],
                  "children": []
                },
                {
                  "id": 111,
                  "label": "Eversion",
                  "type": "img",
                  "buttons": [
                    {
                      "label": "",
                      "img": "Images/eversion.gif"
                    }
                  ],
                  "children": []
                }
              ],
              "type": "none"
            },
            {
              "id": 112,
              "label": "Lateral and Medial Excursion",
              "children": [
                {
                  "id": 113,
                  "label": "Lateral Excursion",
                  "type": "img",
                  "buttons": [
                    {
                      "label": "",
                      "img": "Images/lat_excursion.gif"
                    }
                  ],
                  "children": []
                },
                {
                  "id": 114,
                  "label": "Medial Excursion",
                  "type": "img",
                  "buttons": [
                    {
                      "label": "",
                      "img": "Images/med_excursion.gif"
                    }
                  ],
                  "children": []
                }
              ],
              "type": "none"
            },
            {
              "id": 115,
              "label": "Opposition and Reposition",
              "children": [
                {
                  "id": 116,
                  "label": "Opposition",
                  "type": "img",
                  "buttons": [
                    {
                      "label": "",
                      "img": "Images/opposition.gif"
                    }
                  ],
                  "children": []
                },
                {
                  "id": 117,
                  "label": "Reposition",
                  "type": "img",
                  "buttons": [
                    {
                      "label": "",
                      "img": "Images/reposition.gif"
                    }
                  ],
                  "children": []
                }
              ],
              "type": "none"
            },
            {
              "id": 118,
              "label": "Protraction and Retraction",
              "children": [
                {
                  "id": 119,
                  "label": "Protraction",
                  "type": "img",
                  "buttons": [
                    {
                      "label": "",
                      "img": "Images/protraction.gif"
                    }
                  ],
                  "children": []
                },
                {
                  "id": 120,
                  "label": "Retraction",
                  "type": "img",
                  "buttons": [
                    {
                      "label": "",
                      "img": "Images/retraction.gif"
                    }
                  ],
                  "children": []
                }
              ],
              "type": "none"
            },
            {
              "id": 121,
              "label": "Rotation",
              "children": [
                {
                  "id": 122,
                  "label": "Lateral Rotation",
                  "type": "img",
                  "buttons": [
                    {
                      "label": "",
                      "img": "Images/lateral_rotation.gif"
                    }
                  ],
                  "children": []
                },
                {
                  "id": 123,
                  "label": "Medial Rotation",
                  "type": "img",
                  "buttons": [
                    {
                      "label": "",
                      "img": "Images/medial_rotation.gif"
                    }
                  ],
                  "children": []
                }
              ],
              "type": "none"
            },
            {
              "id": 124,
              "label": "Supination and Pronation",
              "children": [
                {
                  "id": 125,
                  "label": "Supination",
                  "type": "img",
                  "buttons": [
                    {
                      "label": "",
                      "img": "Images/supination.gif"
                    }
                  ],
                  "children": []
                },
                {
                  "id": 126,
                  "label": "Pronation",
                  "type": "img",
                  "buttons": [
                    {
                      "label": "",
                      "img": "Images/pronation.gif"
                    }
                  ],
                  "children": []
                }
              ],
              "type": "none"
            }
          ],
          "type": "none"
        },
        {
          "id": 127,
          "label": "6.1.7 - Hip, Leg, Joints and Movement Videos",
          "children": [
            {
              "id": 128,
              "label": "Os Coxae",
              "children": [],
              "load": "Pages/5_1_4_oscoxae_video_kaylie.html",
              "type": "video",
              "child_items": [
                {
                  "video_link": "https://cdnapisec.kaltura.com/p/1157612/sp/115761200/embedIframeJs/uiconf_id/41338032/partner_id/1157612?iframeembed=true&playerId=kaltura_player&entry_id=1_s9qry5kr&flashvars[localizationCode]=en&amp;flashvars[sideBarContainer.plugin]=true&amp;flashvars[sideBarContainer.position]=left&amp;flashvars[sideBarContainer.clickToClose]=true&amp;flashvars[chapters.plugin]=true&amp;flashvars[chapters.layout]=vertical&amp;flashvars[chapters.thumbnailRotator]=false&amp;flashvars[streamSelector.plugin]=true&amp;flashvars[EmbedPlayer.SpinnerTarget]=videoHolder&amp;flashvars[dualScreen.plugin]=true&amp;flashvars[Kaltura.addCrossoriginToIframe]=true&amp;&wid=1_etz9sn6p"
                }
              ]
            },
            {
              "id": 129,
              "label": "Femur",
              "children": [],
              "load": "Pages/5_1_4_femur_video_kaylie.html",
              "type": "video",
              "child_items": [
                {
                  "video_link": "https://cdnapisec.kaltura.com/p/1157612/sp/115761200/embedIframeJs/uiconf_id/41338032/partner_id/1157612?iframeembed=true&playerId=kaltura_player&entry_id=1_sjehj4ol&flashvars[localizationCode]=en&amp;flashvars[sideBarContainer.plugin]=true&amp;flashvars[sideBarContainer.position]=left&amp;flashvars[sideBarContainer.clickToClose]=true&amp;flashvars[chapters.plugin]=true&amp;flashvars[chapters.layout]=vertical&amp;flashvars[chapters.thumbnailRotator]=false&amp;flashvars[streamSelector.plugin]=true&amp;flashvars[EmbedPlayer.SpinnerTarget]=videoHolder&amp;flashvars[dualScreen.plugin]=true&amp;flashvars[Kaltura.addCrossoriginToIframe]=true&amp;&wid=1_kyparx1c"
                }
              ]
            },
            {
              "id": 130,
              "label": "Patella",
              "children": [],
              "load": "Pages/5_1_4_patella_video_kaylie.html",
              "type": "video",
              "child_items": [
                {
                  "video_link": "https://cdnapisec.kaltura.com/p/1157612/sp/115761200/embedIframeJs/uiconf_id/41338032/partner_id/1157612?iframeembed=true&playerId=kaltura_player&entry_id=1_8ko2awji&flashvars[localizationCode]=en&amp;flashvars[sideBarContainer.plugin]=true&amp;flashvars[sideBarContainer.position]=left&amp;flashvars[sideBarContainer.clickToClose]=true&amp;flashvars[chapters.plugin]=true&amp;flashvars[chapters.layout]=vertical&amp;flashvars[chapters.thumbnailRotator]=false&amp;flashvars[streamSelector.plugin]=true&amp;flashvars[EmbedPlayer.SpinnerTarget]=videoHolder&amp;flashvars[dualScreen.plugin]=true&amp;flashvars[Kaltura.addCrossoriginToIframe]=true&amp;&wid=1_uubiz3xr"
                }
              ]
            },
            {
              "id": 131,
              "label": "Tibia and Fibula",
              "children": [],
              "load": "Pages/5_1_4_tib_fib_video_kaylie.html",
              "type": "video",
              "child_items": [
                {
                  "video_link": "https://cdnapisec.kaltura.com/p/1157612/sp/115761200/embedIframeJs/uiconf_id/41338032/partner_id/1157612?iframeembed=true&playerId=kaltura_player&entry_id=1_9bpdysu8&flashvars[localizationCode]=en&amp;flashvars[sideBarContainer.plugin]=true&amp;flashvars[sideBarContainer.position]=left&amp;flashvars[sideBarContainer.clickToClose]=true&amp;flashvars[chapters.plugin]=true&amp;flashvars[chapters.layout]=vertical&amp;flashvars[chapters.thumbnailRotator]=false&amp;flashvars[streamSelector.plugin]=true&amp;flashvars[EmbedPlayer.SpinnerTarget]=videoHolder&amp;flashvars[dualScreen.plugin]=true&amp;flashvars[Kaltura.addCrossoriginToIframe]=true&amp;&wid=1_y4kqz0kt"
                }
              ]
            },
            {
              "id": 132,
              "label": "Joints",
              "children": [],
              "load": "Pages/5_1_4_joints_kaylie.html"
            },
            {
              "id": 133,
              "label": "Movements",
              "children": [],
              "load": "Pages/5_1_4_movements_kaylie.html"
            }
          ],
          "type": "none"
        }
      ]
    },
    {
      "id": "week-6-2-practice",
      "title": "WEEK 6.2 - PRACTICE",
      "data": [
        {
          "id": 134,
          "label": "WEEK 6.2 - PRACTICE",
          "children": [],
          "type": "none"
        },
        {
          "id": 135,
          "label": "6.2.1 - Descriptions",
          "load": "Pages/6_2_1_descriptions.html",
          "children": []
        },
        {
          "id": 136,
          "label": "6.2.2 - Practice with 3D",
          "load": "Pages/5_2_2_3D_leg_practice_intro.html",
          "type": "none",
          "children": [
            {
              "id": 137,
              "label": "Clickable Leg Bones",
              "type": "none",
              "child_items": [
                {
                  "page": "https://content.byui.edu/file/626b8143-29d0-4415-8e30-d7107faa72f4/1/Leg%20Bones%20Clickable/index.html"
                }
              ],
              "children": []
            },
            {
              "id": 138,
              "label": "Find on the Leg Boones",
              "type": "none",
              "child_items": [
                {
                  "page": "https://content.byui.edu/file/626b8143-29d0-4415-8e30-d7107faa72f4/1/Leg%20Bone%20Find/index.html"
                }
              ],
              "children": []
            }
          ]
        },
        {
          "id": 139,
          "label": "6.2.3 - Try Naming Some Pictures",
          "load": "powerpoint/legs_pelvis/index.html",
          "children": []
        },
        {
          "id": 140,
          "label": "6.2.4 - Flashcards",
          "children": [],
          "type": "none",
          "child_items": [
            {
              "page": "https://content.byui.edu/file/7be1c52f-c2a4-4d40-a709-65b9d0554453/1/flashcards2_build/index.html"
            }
          ]
        }
      ]
    }
  ]
}
